matrixllm/__init__.py
matrixllm/mcp_server.py
matrixllm/api/__init__.py
matrixllm/api/auth.py
matrixllm/api/main.py
matrixllm/api/pair.py
matrixllm/api/relay.py
matrixllm/api/schemas.py
matrixllm/api/state.py
matrixllm/cli/__init__.py
matrixllm/cli/__main__.py
matrixllm/cli/main.py
matrixllm/cloud/__init__.py
matrixllm/cloud/api_client.py
matrixllm/cloud/device_config.py
matrixllm/connectors/__init__.py
matrixllm/connectors/base.py
matrixllm/connectors/direct_endpoint.py
matrixllm/core/__init__.py
matrixllm/core/enrollment.py
matrixllm/core/keys.py
matrixllm/core/pairing.py
matrixllm/core/policy_router.py
matrixllm/core/registry.py
matrixllm/core/router.py
matrixllm/core/security.py
matrixllm/core/settings.py
matrixllm/db/__init__.py
matrixllm/db/database.py
matrixllm/db/models.py
matrixllm/mcp/__init__.py
matrixllm/mcp/server.py
matrixllm/mcp/tools.py
matrixllm/node/__init__.py
matrixllm/node/agent.py
matrixllm/node/cli.py
matrixllm/node/runtime.py
matrixllm/providers/__init__.py
matrixllm/providers/anthropic_provider.py
matrixllm/providers/base.py
matrixllm/providers/gemini_provider.py
matrixllm/providers/matrixnode_provider.py
matrixllm/providers/ollama_client.py
matrixllm/providers/openai_compat.py
matrixllm/providers/watsonx_provider.py
matrixllm/utils/__init__.py
matrixllm/utils/installer.py
matrixllm/utils/tunnel.py
matrixllm-0.1.1.dist-info/METADATA
matrixllm-0.1.1.dist-info/WHEEL
matrixllm-0.1.1.dist-info/entry_points.txt
matrixllm-0.1.1.dist-info/licenses/LICENSE
matrixllm-0.1.1.dist-info/RECORD
