Metadata-Version: 2.4
Name: matrixllm
Version: 0.1.1
Summary: MatrixLLM: OpenAI-compatible multi-provider LLM router (OpenRouter-style) with optional relay nodes
Project-URL: Homepage, https://github.com/agent-matrix/matrix-llm
Project-URL: Documentation, https://github.com/agent-matrix/matrix-llm#readme
Project-URL: Repository, https://github.com/agent-matrix/matrix-llm
Project-URL: Issues, https://github.com/agent-matrix/matrix-llm/issues
Project-URL: Changelog, https://github.com/agent-matrix/matrix-llm/releases
Author-email: Ruslan Magana Vsevolodovna <contact@ruslanmv.com>
Maintainer-email: Ruslan Magana Vsevolodovna <contact@ruslanmv.com>
License: 
License-File: LICENSE
Keywords: ai,anthropic,api,chatgpt,deepseek,embeddings,gateway,gemini,langchain,llama,llm,machine-learning,multi-provider,ollama,openai,openrouter,router,self-hosted,watsonx
Classifier: Development Status :: 4 - Beta
Classifier: Framework :: FastAPI
Classifier: Intended Audience :: Developers
Classifier: Intended Audience :: Science/Research
Classifier: License :: OSI Approved :: Apache Software License
Classifier: Operating System :: OS Independent
Classifier: Programming Language :: Python :: 3
Classifier: Programming Language :: Python :: 3.10
Classifier: Programming Language :: Python :: 3.11
Classifier: Programming Language :: Python :: 3.12
Classifier: Topic :: Internet :: WWW/HTTP :: HTTP Servers
Classifier: Topic :: Scientific/Engineering :: Artificial Intelligence
Classifier: Topic :: Software Development :: Libraries :: Python Modules
Requires-Python: >=3.10
Requires-Dist: anyio
Requires-Dist: fastapi>=0.110
Requires-Dist: httpx>=0.26
Requires-Dist: itsdangerous>=2.1
Requires-Dist: pydantic-settings>=2.2
Requires-Dist: pydantic>=2.6
Requires-Dist: python-dotenv>=1.0
Requires-Dist: pyyaml>=6.0
Requires-Dist: rich>=13.7
Requires-Dist: slowapi
Requires-Dist: sqlalchemy
Requires-Dist: sqlmodel
Requires-Dist: tenacity>=8.2
Requires-Dist: typer>=0.12
Requires-Dist: uvicorn[standard]>=0.27
Requires-Dist: websockets>=12.0
Provides-Extra: dev
Requires-Dist: black>=23.7; extra == 'dev'
Requires-Dist: mypy>=1.4; extra == 'dev'
Requires-Dist: pytest-asyncio>=0.21; extra == 'dev'
Requires-Dist: pytest-cov>=4.1; extra == 'dev'
Requires-Dist: pytest>=7.4; extra == 'dev'
Requires-Dist: ruff>=0.0.280; extra == 'dev'
Provides-Extra: notebook
Requires-Dist: ipykernel>=7.1.0; extra == 'notebook'
Requires-Dist: nbclient>=0.10.0; extra == 'notebook'
Requires-Dist: nbconvert>=7.0.0; extra == 'notebook'
Requires-Dist: openai>=1.14.0; extra == 'notebook'
Requires-Dist: python-dotenv>=1.0.1; extra == 'notebook'
Requires-Dist: requests>=2.32.0; extra == 'notebook'
